fork.py
xfork-0.37.dist-info/METADATA
xfork-0.37.dist-info/WHEEL
xfork-0.37.dist-info/top_level.txt
xfork-0.37.dist-info/metadata.json
xfork-0.37.dist-info/RECORD
xfork-0.37.dist-info/DESCRIPTION.rst
