Metadata-Version: 2.0
Name: xfork
Version: 0.37
Summary: submitting cpu-bound tasks to processes and io-bound tasks to threads
Home-page: https://github.com/srkunze/fork
Author: Sven R. Kunze
Author-email: srkunze@mail.de
License: MIT
Platform: UNKNOWN
Classifier: Development Status :: 2 - Pre-Alpha
Classifier: Intended Audience :: Developers
Classifier: License :: OSI Approved :: MIT License
Classifier: Programming Language :: Python
